inte_prn/__init__.py
inte_prn/action_items.py
inte_prn/admin_site.py
inte_prn/apps.py
inte_prn/choices.py
inte_prn/constants.py
inte_prn/urls.py
inte_prn/views.py
inte_prn/admin/__init__.py
inte_prn/admin/autocomplete_admin.py
inte_prn/admin/end_of_study_admin.py
inte_prn/admin/onschedule_admin.py
inte_prn/admin/protocol_deviation_violation_admin.py
inte_prn/admin/unblinding_request_admin.py
inte_prn/admin/unblinding_review_admin.py
inte_prn/form_validators/__init__.py
inte_prn/form_validators/death_report.py
inte_prn/form_validators/end_of_study.py
inte_prn/form_validators/protocol_deviation_violation.py
inte_prn/form_validators/study_day_form_validator_mixin.py
inte_prn/form_validators/validate_death_report_mixin.py
inte_prn/forms/__init__.py
inte_prn/forms/end_of_study_form.py
inte_prn/forms/loss_to_followup.py
inte_prn/forms/protocol_deviation_violation_form.py
inte_prn/forms/unblinding_request_form.py
inte_prn/forms/unblinding_review_form.py
inte_prn/migrations/0001_initial.py
inte_prn/migrations/__init__.py
inte_prn/models/__init__.py
inte_prn/models/base_study_termination.py
inte_prn/models/end_of_study.py
inte_prn/models/loss_to_followup.py
inte_prn/models/onschedule.py
inte_prn/models/protocol_deviation_violation.py
inte_prn/models/unblinding_request.py
inte_prn/models/unblinding_review.py
inte_prn/models/unblinding_user.py
inte_prn/tests/__init__.py
inte_prn/tests/urls.py
inte_prn/tests/tests/__init__.py
inte_prn-0.1.3.dist-info/AUTHORS
inte_prn-0.1.3.dist-info/LICENSE
inte_prn-0.1.3.dist-info/METADATA
inte_prn-0.1.3.dist-info/WHEEL
inte_prn-0.1.3.dist-info/top_level.txt
inte_prn-0.1.3.dist-info/RECORD
